mkdocs_katex_ssr/plugin.py
mkdocs_katex_ssr/renderer.js
mkdocs_katex_ssr-1.0.5.dist-info/licenses/LICENSE
mkdocs_katex_ssr-1.0.5.dist-info/METADATA
mkdocs_katex_ssr-1.0.5.dist-info/WHEEL
mkdocs_katex_ssr-1.0.5.dist-info/entry_points.txt
mkdocs_katex_ssr-1.0.5.dist-info/top_level.txt
mkdocs_katex_ssr-1.0.5.dist-info/RECORD
