Metadata-Version: 2.4
Name: mkdocs-katex-ssr
Version: 1.0.5
Summary: A MkDocs plugin for server-side rendering of KaTeX math.
Author-email: RainPPR <2125773894@qq.com>
License-Expression: MIT
Project-URL: Homepage, https://raineblog.dpdns.org/mkdocs-katex-ssr/
Project-URL: Documentation, https://raineblog.dpdns.org/mkdocs-katex-ssr/configuration/
Project-URL: Repository, https://github.com/raineblog/mkdocs-katex-ssr
Project-URL: Issues, https://github.com/raineblog/mkdocs-katex-ssr/issues
License-File: LICENSE
Requires-Dist: mkdocs>=1.1.0
Requires-Dist: beautifulsoup4>=4.9.0
Dynamic: license-file
